factorial_app_testing/__init__.py
factorial_app_testing/app.py
factorial_app_testing/factorial.py
factorial_app_testing-0.1.0.dist-info/METADATA
factorial_app_testing-0.1.0.dist-info/WHEEL
factorial_app_testing-0.1.0.dist-info/RECORD
